chalice_a4ab/__init__.py
chalice_a4ab/agents_for_amazon_bedrock_config.py
chalice_a4ab/chalice_plugin.py
chalice_a4ab/cli/__init__.py
chalice_a4ab/cli/agent_model.py
chalice_a4ab/cli/arg_input.py
chalice_a4ab/cli/cdk.py
chalice_a4ab/cli/management.py
chalice_a4ab/cli/run_agent.py
chalice_a4ab/cli/template.yaml
chalice_a4ab/model_types.py
chalice_a4ab/runtime/__init__.py
chalice_a4ab/runtime/api_runtime.py
chalice_a4ab/runtime/converter/__init__.py
chalice_a4ab/runtime/converter/bedrock_agent_event_to_apigw.py
chalice_a4ab/runtime/model_utility/apigw.py
chalice_a4ab/runtime/model_utility/bedrock_agent.py
chalice_a4ab/runtime/models/apigw.py
chalice_a4ab/runtime/models/bedrock_agent.py
chalice_a4ab/runtime/models/parser_lambda.py
chalice_a4ab/runtime/parser_lambda/agents_parser.py
chalice_a4ab/runtime/parser_lambda/amazon_example/NOTE.txt
chalice_a4ab/runtime/parser_lambda/amazon_example/orchestration.py
chalice_a4ab/runtime/parser_lambda/amazon_example/post_processing.py
chalice_a4ab/runtime/parser_lambda/amazon_example/pre_processing.py
chalice_a4ab/runtime/parser_lambda/amazon_example/v2_1/orchestration.py
chalice_a4ab/runtime/parser_lambda/exceptions.py
chalice_a4ab/runtime/parser_lambda/invoke_utility.py
chalice_a4ab/runtime/pydantic_tool/utility.py
chalice_a4ab/utility/parser.py
chalice_a4ab-0.3.1.dist-info/entry_points.txt
chalice_a4ab-0.3.1.dist-info/LICENSE
chalice_a4ab-0.3.1.dist-info/METADATA
chalice_a4ab-0.3.1.dist-info/WHEEL
chalice_a4ab-0.3.1.dist-info/RECORD
