Metadata-Version: 2.1
Name: chalice-a4ab
Version: 0.3.1
Summary: Chalice x Agents for Amazon Bedrock plug-ins
Home-page: https://github.com/ShotaOki/ChaliceA4AB
License: MIT
Keywords: Chalice,AWS,Agents for Amazon Bedrock,Bedrock
Author: Shota Oki
Requires-Python: >=3.8,<4.0
Classifier: License :: OSI Approved :: MIT License
Classifier: Programming Language :: Python :: 3
Classifier: Programming Language :: Python :: 3.8
Classifier: Programming Language :: Python :: 3.9
Classifier: Programming Language :: Python :: 3.10
Classifier: Programming Language :: Python :: 3.11
Classifier: Programming Language :: Python :: 3.12
Requires-Dist: apispec (>=6.0.2,<7.0.0)
Requires-Dist: chalice-spec (>=0.7.0,<0.8.0)
Project-URL: Repository, https://github.com/ShotaOki/ChaliceA4AB
